pybfc/__init__.py
pybfc/__main__.py
pybfc/main.py
pybfc/version.py
pybfc/bfctypes/__init__.py
pybfc/bfctypes/main.py
pybfc/exceptions/__init__.py
pybfc/exceptions/main.py
pybfc-0.0.0.dist-info/LICENSE
pybfc-0.0.0.dist-info/METADATA
pybfc-0.0.0.dist-info/WHEEL
pybfc-0.0.0.dist-info/entry_points.txt
pybfc-0.0.0.dist-info/top_level.txt
pybfc-0.0.0.dist-info/RECORD
