Metadata-Version: 2.1
Name: pybfc
Version: 0.0.0
Summary: BranFuck compiler write in python
Home-page: https://github.com/TheAwiteb/pybfc
Author: Awiteb
Author-email: Awiteb@hotmail.com
License: AGPLv3
Project-URL: Bug Reports, https://github.com/TheAwiteb/pybfc/issues/new?assignees=&labels=bug&template=bug.md
Project-URL: Source Code, https://github.com/TheAwiteb/pybfc
Keywords: pybfc,BF,branfuck,branfuck_compiler,branfuck_interprater
Platform: UNKNOWN
Classifier: Programming Language :: Python :: 3.8
Classifier: Programming Language :: Python :: 3.9
Classifier: Programming Language :: Python :: 3.10
Classifier: License :: OSI Approved :: GNU Affero General Public License v3
Classifier: Operating System :: OS Independent
Requires-Python: >=3.8
License-File: LICENSE
Requires-Dist: click (==8.0.3)
Requires-Dist: pydantic (==1.9.0)
Requires-Dist: typer (==0.4.0)
Requires-Dist: typing-extensions (==4.0.1)
